replapi_it/__init__.py
replapi_it-0.0.1.dist-info/LICENSE
replapi_it-0.0.1.dist-info/WHEEL
replapi_it-0.0.1.dist-info/METADATA
replapi_it-0.0.1.dist-info/RECORD
