Metadata-Version: 2.1
Name: replapi-it
Version: 0.0.1
Summary: ReplAPI-It for Python
Home-page: https://github.com/ReplAPI-it/Python-ReplAPI-It
License: GPL-3.0-only
Author: BD103
Author-email: dont@stalk.me
Requires-Python: >=3.8,<4.0
Classifier: License :: OSI Approved :: GNU General Public License v3 (GPLv3)
Classifier: Programming Language :: Python :: 3
Classifier: Programming Language :: Python :: 3.8
Project-URL: Repository, https://github.com/ReplAPI-it/Python-ReplAPI-It
